typer/__init__.py
typer/_compat_utils.py
typer/_completion_click7.py
typer/_completion_click8.py
typer/_completion_shared.py
typer/_typing.py
typer/colors.py
typer/completion.py
typer/core.py
typer/main.py
typer/models.py
typer/params.py
typer/py.typed
typer/rich_utils.py
typer/testing.py
typer/utils.py
gage_typer-0.9.0.dist-info/WHEEL
gage_typer-0.9.0.dist-info/METADATA
gage_typer-0.9.0.dist-info/RECORD
