Metadata-Version: 2.1
Name: gage-typer
Version: 0.9.0
Summary: Typer, build great CLIs. Easy to code. Based on Python type hints.
Home-page: https://github.com/tiangolo/typer
License: UNKNOWN
Author: Sebastián Ramírez
Author-email: tiangolo@gmail.com
Requires-Python: >=3.6
Classifier: Intended Audience :: Information Technology
Classifier: Intended Audience :: System Administrators
Classifier: Operating System :: OS Independent
Classifier: Programming Language :: Python :: 3
Classifier: Programming Language :: Python
Classifier: Topic :: Software Development :: Libraries :: Application Frameworks
Classifier: Topic :: Software Development :: Libraries :: Python Modules
Classifier: Topic :: Software Development :: Libraries
Classifier: Topic :: Software Development
Classifier: Typing :: Typed
Classifier: Development Status :: 4 - Beta
Classifier: Intended Audience :: Developers
Classifier: Programming Language :: Python :: 3 :: Only
Classifier: Programming Language :: Python :: 3.6
Classifier: Programming Language :: Python :: 3.7
Classifier: Programming Language :: Python :: 3.8
Classifier: Programming Language :: Python :: 3.9
Classifier: Programming Language :: Python :: 3.10
Classifier: Programming Language :: Python :: 3.11
Classifier: License :: OSI Approved :: MIT License
Requires-Dist: click >= 7.1.1, <9.0.0
Requires-Dist: typing-extensions >= 3.7.4.3
Requires-Dist: colorama >=0.4.3,<0.5.0 ; extra == "all"
Requires-Dist: shellingham >=1.3.0,<2.0.0 ; extra == "all"
Requires-Dist: rich >=10.11.0,<14.0.0 ; extra == "all"
Requires-Dist: autoflake >=1.3.1,<2.0.0 ; extra == "dev"
Requires-Dist: flake8 >=3.8.3,<4.0.0 ; extra == "dev"
Requires-Dist: pre-commit >=2.17.0,<3.0.0 ; extra == "dev"
Requires-Dist: mkdocs >=1.1.2,<2.0.0 ; extra == "doc"
Requires-Dist: mkdocs-material >=8.1.4,<9.0.0 ; extra == "doc"
Requires-Dist: mdx-include >=1.4.1,<2.0.0 ; extra == "doc"
Requires-Dist: pillow >=9.3.0,<10.0.0 ; extra == "doc"
Requires-Dist: cairosvg >=2.5.2,<3.0.0 ; extra == "doc"
Requires-Dist: shellingham >=1.3.0,<2.0.0 ; extra == "test"
Requires-Dist: pytest >=4.4.0,<8.0.0 ; extra == "test"
Requires-Dist: pytest-cov >=2.10.0,<5.0.0 ; extra == "test"
Requires-Dist: coverage >=6.2,<7.0 ; extra == "test"
Requires-Dist: pytest-xdist >=1.32.0,<4.0.0 ; extra == "test"
Requires-Dist: pytest-sugar >=0.9.4,<0.10.0 ; extra == "test"
Requires-Dist: mypy ==0.971 ; extra == "test"
Requires-Dist: black >=22.3.0,<23.0.0 ; extra == "test"
Requires-Dist: isort >=5.0.6,<6.0.0 ; extra == "test"
Requires-Dist: rich >=10.11.0,<14.0.0 ; extra == "test"
Project-URL: Documentation, https://typer.tiangolo.com/
Provides-Extra: all
Provides-Extra: dev
Provides-Extra: doc
Provides-Extra: test
